Metadata-Version: 2.1
Name: yaspeak
Version: 0.0.1
Summary: Python wrapper for Yandex text voiceover
Home-page: https://github.com/dmitrijkotov634/YaSpeak
Author: dmitrijkotov
Author-email: dmitrijkotov634@mail.ru
License: MIT
Keywords: speak
Platform: UNKNOWN
Classifier: Programming Language :: Python :: 3
Classifier: Programming Language :: Python :: 3.4
Classifier: Programming Language :: Python :: 3.5
Classifier: Programming Language :: Python :: 3.6
Classifier: Programming Language :: Python :: 3.7
Classifier: License :: OSI Approved :: MIT License
Classifier: Operating System :: OS Independent
Requires-Python: >=3
